odtemplater/__init__.py
odtemplater/app.py
odtemplater/odt_engine.py
odtemplater/config/__init__.py
odtemplater/config/config.py
odtemplater/lib/__init__.py
odtemplater/lib/lib.py
odtemplater/odtapplysettings/__init__.py
odtemplater/odtapplysettings/my_odt_checker_anchor.py
odtemplater/odtapplysettings/odt_apply_settings.py
odtemplater/odtapplysettings/setting_add_images.py
odtemplater/odtapplysettings/setting_extend_diagram.py
odtemplater/odtapplysettings/setting_extend_set.py
odtemplater/odtapplysettings/setting_if_block.py
odtemplater-0.0.1.dist-info/METADATA
odtemplater-0.0.1.dist-info/WHEEL
odtemplater-0.0.1.dist-info/top_level.txt
odtemplater-0.0.1.dist-info/RECORD
