Metadata-Version: 2.1
Name: odtemplater
Version: 0.0.1
Summary: ODT file template engine
Author-email: myzxzrus <myzxzrus@gmail.com>
Project-URL: Homepage, https://github.com/myzxzrus/ODTemplater
Project-URL: Bug Tracker, https://github.com/myzxzrus/ODTemplater/issues
Classifier: Programming Language :: Python :: 3
Classifier: License :: OSI Approved :: MIT License
Classifier: Operating System :: POSIX :: Linux
Requires-Python: >=3.7
Requires-Dist: Pillow (>=8.0.1)
